ol_openedx_chat_xblock/__init__.py
ol_openedx_chat_xblock/apps.py
ol_openedx_chat_xblock/block.py
ol_openedx_chat_xblock/constants.py
ol_openedx_chat_xblock/filters.py
ol_openedx_chat_xblock/settings/common.py
ol_openedx_chat_xblock/settings/devstack.py
ol_openedx_chat_xblock/static/css/ai_chat_xblock.css
ol_openedx_chat_xblock/static/html/student_view.html
ol_openedx_chat_xblock/static/html/studio_view.html
ol_openedx_chat_xblock/static/js/lms.js
ol_openedx_chat_xblock/static/js/studio.js
ol_openedx_chat_xblock-0.4.5.dist-info/METADATA
ol_openedx_chat_xblock-0.4.5.dist-info/WHEEL
ol_openedx_chat_xblock-0.4.5.dist-info/entry_points.txt
ol_openedx_chat_xblock-0.4.5.dist-info/licenses/LICENSE
ol_openedx_chat_xblock-0.4.5.dist-info/RECORD
