Metadata-Version: 2.4
Name: ol-openedx-chat-xblock
Version: 0.4.5
Summary: An Open edX xBlock to add Open Learning AI chat
Project-URL: Homepage, https://github.com/mitodl/edx-extensions
Author-email: MIT Office of Digital Learning <odl@mit.edu>
License: BSD-3-Clause
License-File: LICENSE
Keywords: Python,edx
Requires-Python: >=3.11
Requires-Dist: django>=3.2
Requires-Dist: djangorestframework>=3.14.0
Requires-Dist: edx-django-utils>=1.3.0
Requires-Dist: xblock-utils>=1.2.0
Requires-Dist: xblock>=1.9.0
